timefile/__init__.py
timefile/config.py
timefile/helpers.py
timefile/logger.py
timefile/models.py
timefile/plotter.py
timefile-0.1.1.dist-info/LICENSE
timefile-0.1.1.dist-info/METADATA
timefile-0.1.1.dist-info/WHEEL
timefile-0.1.1.dist-info/RECORD
