Metadata-Version: 2.1
Name: timefile
Version: 0.1.1
Summary: Probably the simplest time profiling in python
Home-page: https://github.com/hugofe99/timefile
License: MIT
Author: hugofe99
Author-email: fernstrom.hugo@gmail.com
Requires-Python: >=3.9,<4.0
Classifier: License :: OSI Approved :: MIT License
Classifier: Programming Language :: Python :: 3
Classifier: Programming Language :: Python :: 3.9
Classifier: Programming Language :: Python :: 3.10
Classifier: Programming Language :: Python :: 3.11
Classifier: Programming Language :: Python :: 3.12
Requires-Dist: matplotlib (>=3.8.2)
Project-URL: Repository, https://github.com/hugofe99/timefile
